Metadata-Version: 2.1
Name: cookiedb-cli
Version: 0.3.0
Summary: The CLI for interactive use of CookieDB. 
Home-page: https://github.com/jaedsonpys/cookiedb-cli
Author: Jaedson Silva
Author-email: imunknowuser@protonmail.com
License: GPL
Project-URL: Source code, https://github.com/jaedsonpys/cookiedb-cli
Project-URL: License, https://github.com/jaedsonpys/cookiedb-cli/blob/master/LICENSE
Keywords: database,cli,console,cookiedb
Classifier: License :: OSI Approved :: GNU General Public License v3 (GPLv3)
Classifier: Development Status :: 5 - Production/Stable
Classifier: Intended Audience :: Developers
Classifier: Intended Audience :: System Administrators
Classifier: Intended Audience :: Science/Research
Classifier: Natural Language :: English
Classifier: Operating System :: OS Independent
Classifier: Programming Language :: Python :: 3
Classifier: Topic :: Database
Classifier: Topic :: Database :: Database Engines/Servers
Requires-Python: >=3.6
License-File: LICENSE
